LICENSE
blacksheep_context/__init__.py
blacksheep_context/ctx.py
blacksheep_context/errors.py
blacksheep_context/middleware.py
blacksheep_context/plugins/__init__.py
blacksheep_context/plugins/base.py
blacksheep_context/plugins/header.py
blacksheep_context/py.typed
blacksheep_context-0.1.0.dist-info/LICENSE
blacksheep_context-0.1.0.dist-info/WHEEL
blacksheep_context-0.1.0.dist-info/METADATA
blacksheep_context-0.1.0.dist-info/RECORD
