Metadata-Version: 2.1
Name: blacksheep-context
Version: 0.1.0
Summary: Middleware for blacksheep that allows you to store and access the context data of a request.
Home-page: https://github.com/Cdayz/blacksheep-context
License: MIT
Keywords: blacksheep,context,middleware,blacksheep-context
Author: Nikita Tomchik
Author-email: cdayz@yandex.ru
Requires-Python: >=3.7,<4.0
Classifier: Development Status :: 5 - Production/Stable
Classifier: Intended Audience :: Developers
Classifier: License :: OSI Approved :: MIT License
Classifier: Programming Language :: Python :: 3
Classifier: Programming Language :: Python :: 3.7
Classifier: Programming Language :: Python :: 3.8
Classifier: Programming Language :: Python :: 3.9
Classifier: Topic :: Internet :: WWW/HTTP :: HTTP Servers
Classifier: Topic :: Software Development
Classifier: Topic :: Software Development :: Libraries
Requires-Dist: blacksheep (>=1.0.7)
Project-URL: Repository, https://github.com/Cdayz/blacksheep-context
